Metadata-Version: 2.1
Name: snipco
Version: 0.2.1
Summary: A command-line clipboard utility and snippet catalog
Home-page: https://github.com/Abstrys/snipco/
Author: Eron Hennessey
Author-email: eron@abstrys.com
License: BSD
Keywords: clipboard snip
Platform: UNKNOWN
Classifier: Development Status :: 3 - Alpha
Classifier: Topic :: Utilities
Classifier: License :: OSI Approved :: BSD License
